{"version": 0.6, "generator": "Overpass API 0.7.62.5 1bd436f1", "osm3s": {"timestamp_osm_base": "2025-03-28T12:34:05Z", "copyright": "The data included in this document is from www.openstreetmap.org. The data is made available under ODbL."}, "elements": [{"type": "node", "id": 26925945, "lat": 65.6188933, "lon": 44.6503}, {"type": "node", "id": 26925952, "lat": 65.6086174, "lon": 44.6676313}, {"type": "node", "id": 26925953, "lat": 65.6073889, "lon": 44.6698943}, {"type": "node", "id": 26925954, "lat": 65.6057857, "lon": 44.6730621}, {"type": "node", "id": 26925955, "lat": 65.6043015, "lon": 44.6759242}, {"type": "node", "id": 26925956, "lat": 65.6033767, "lon": 44.6773053}, {"type": "node", "id": 26926251, "lat": 65.6022374, "lon": 44.6787064}, {"type": "node", "id": 26926252, "lat": 65.6012752, "lon": 44.6798422}, {"type": "node", "id": 26926253, "lat": 65.6000679, "lon": 44.6812791}, {"type": "node", "id": 26926254, "lat": 65.5983283, "lon": 44.6833817}, {"type": "node", "id": 26926255, "lat": 65.5966639, "lon": 44.6853647}, {"type": "node", "id": 26926256, "lat": 65.5942706, "lon": 44.6882354}, {"type": "node", "id": 26926257, "lat": 65.5921434, "lon": 44.6908011}, {"type": "node", "id": 26926258, "lat": 65.5899964, "lon": 44.6934152}, {"type": "node", "id": 26926259, "lat": 65.5876056, "lon": 44.6962995}, {"type": "node", "id": 26926260, "lat": 65.585764, "lon": 44.6986214}, {"type": "node", "id": 26926261, "lat": 65.58448, "lon": 44.7005355}, {"type": "node", "id": 26926262, "lat": 65.5837278, "lon": 44.7021985}, {"type": "node", "id": 26926263, "lat": 65.5824177, "lon": 44.7052108}, {"type": "node", "id": 26926264, "lat": 65.5807833, "lon": 44.7090075}, {"type": "node", "id": 26926265, "lat": 65.5795899, "lon": 44.711706}, {"type": "node", "id": 26926266, "lat": 65.5785082, "lon": 44.7141764}, {"type": "node", "id": 26926267, "lat": 65.5772532, "lon": 44.7170678}, {"type": "node", "id": 26926268, "lat": 65.5759771, "lon": 44.7200106}, {"type": "node", "id": 26926269, "lat": 65.5749064, "lon": 44.7233158}, {"type": "node", "id": 26926270, "lat": 65.5738212, "lon": 44.7268309}, {"type": "node", "id": 26926271, "lat": 65.5726626, "lon": 44.7304589}, {"type": "node", "id": 26926272, "lat": 65.57193, "lon": 44.7327021}, {"type": "node", "id": 26926273, "lat": 65.5716731, "lon": 44.7334039}, {"type": "node", "id": 26926274, "lat": 65.571364, "lon": 44.7340156}, {"type": "node", "id": 26926275, "lat": 65.5711237, "lon": 44.7343023}, {"type": "node", "id": 26926276, "lat": 65.5707671, "lon": 44.7345176}, {"type": "node", "id": 26926277, "lat": 65.5703918, "lon": 44.7345909}, {"type": "node", "id": 26926278, "lat": 65.5687059, "lon": 44.7345515}, {"type": "node", "id": 26926279, "lat": 65.5667439, "lon": 44.7344235}, {"type": "node", "id": 26926280, "lat": 65.5646802, "lon": 44.7343607}, {"type": "node", "id": 26926281, "lat": 65.5625406, "lon": 44.734271}, {"type": "node", "id": 26926282, "lat": 65.5606075, "lon": 44.7341848}, {"type": "node", "id": 26926283, "lat": 65.5581093, "lon": 44.7340083}, {"type": "node", "id": 26926284, "lat": 65.556125, "lon": 44.7338587}, {"type": "node", "id": 26926285, "lat": 65.5543862, "lon": 44.7338048}, {"type": "node", "id": 26926286, "lat": 65.5529274, "lon": 44.7337259}, {"type": "node", "id": 26926287, "lat": 65.5513854, "lon": 44.7336426}, {"type": "node", "id": 26926288, "lat": 65.5493916, "lon": 44.7335098}, {"type": "node", "id": 26926289, "lat": 65.5471774, "lon": 44.7332939}, {"type": "node", "id": 26926290, "lat": 65.5453492, "lon": 44.7331566}, {"type": "node", "id": 26926291, "lat": 65.5435035, "lon": 44.7330437}, {"type": "node", "id": 26926292, "lat": 65.5424621, "lon": 44.7329487}, {"type": "node", "id": 26926293, "lat": 65.5413377, "lon": 44.7328718}, {"type": "node", "id": 26926294, "lat": 65.5400705, "lon": 44.7329085}, {"type": "node", "id": 26926295, "lat": 65.539383, "lon": 44.7332939}, {"type": "node", "id": 26926296, "lat": 65.5385482, "lon": 44.7340319}, {"type": "node", "id": 26926297, "lat": 65.537822, "lon": 44.7349478}, {"type": "node", "id": 26926298, "lat": 65.5366344, "lon": 44.736488}, {"type": "node", "id": 26926299, "lat": 65.5351408, "lon": 44.7384927}, {"type": "node", "id": 26926300, "lat": 65.5335181, "lon": 44.7406934}, {"type": "node", "id": 26926301, "lat": 65.533118, "lon": 44.7413022}, {"type": "node", "id": 26926302, "lat": 65.5325862, "lon": 44.7425968}, {"type": "node", "id": 26926303, "lat": 65.5322635, "lon": 44.7435785}, {"type": "node", "id": 26926304, "lat": 65.531681, "lon": 44.7460862}, {"type": "node", "id": 26926305, "lat": 65.5304426, "lon": 44.7514303}, {"type": "node", "id": 26926306, "lat": 65.5295068, "lon": 44.7556976}, {"type": "node", "id": 26926307, "lat": 65.5284889, "lon": 44.7600385}, {"type": "node", "id": 26926308, "lat": 65.5276762, "lon": 44.7635557}, {"type": "node", "id": 26926309, "lat": 65.5273536, "lon": 44.7652965}, {"type": "node", "id": 26926310, "lat": 65.5269759, "lon": 44.7680567}, {"type": "node", "id": 26926311, "lat": 65.5267612, "lon": 44.7702176}, {"type": "node", "id": 26926312, "lat": 65.5266825, "lon": 44.7726181}, {"type": "node", "id": 26926313, "lat": 65.5265849, "lon": 44.7763083}, {"type": "node", "id": 26926314, "lat": 65.526423, "lon": 44.7816619}, {"type": "node", "id": 26926315, "lat": 65.5262509, "lon": 44.7845278}, {"type": "node", "id": 26926316, "lat": 65.5259713, "lon": 44.7866989}, {"type": "node", "id": 26926317, "lat": 65.5255369, "lon": 44.7901132}, {"type": "node", "id": 26926318, "lat": 65.5251913, "lon": 44.7933196}, {"type": "node", "id": 26926319, "lat": 65.5245933, "lon": 44.7991873}, {"type": "node", "id": 26926320, "lat": 65.5241513, "lon": 44.8037998}, {"type": "node", "id": 26926321, "lat": 65.523773, "lon": 44.8078336}, {"type": "node", "id": 26926322, "lat": 65.5233875, "lon": 44.8117802}, {"type": "node", "id": 26926323, "lat": 65.5229813, "lon": 44.8157234}, {"type": "node", "id": 26926324, "lat": 65.5224865, "lon": 44.8209}, {"type": "node", "id": 26926325, "lat": 65.5219201, "lon": 44.8265567}, {"type": "node", "id": 26926326, "lat": 65.5214141, "lon": 44.8316006}, {"type": "node", "id": 26926327, "lat": 65.5209206, "lon": 44.8367079}, {"type": "node", "id": 26926328, "lat": 65.5204731, "lon": 44.8414272}, {"type": "node", "id": 26926329, "lat": 65.5200624, "lon": 44.8454624}, {"type": "node", "id": 26926330, "lat": 65.5197762, "lon": 44.8475226}, {"type": "node", "id": 26926331, "lat": 65.5192929, "lon": 44.8504425}, {"type": "node", "id": 26926332, "lat": 65.5184009, "lon": 44.8558422}, {"type": "node", "id": 26926333, "lat": 65.5175034, "lon": 44.8608411}, {"type": "node", "id": 26926334, "lat": 65.5171686, "lon": 44.8626807}, {"type": "node", "id": 26926335, "lat": 65.5169139, "lon": 44.8644949}, {"type": "node", "id": 26926336, "lat": 65.5166507, "lon": 44.8673407}, {"type": "node", "id": 26926337, "lat": 65.5164607, "lon": 44.8717864}, {"type": "node", "id": 26926338, "lat": 65.5163008, "lon": 44.8763974}, {"type": "node", "id": 26926339, "lat": 65.5162992, "lon": 44.8821222}, {"type": "node", "id": 26926340, "lat": 65.5163735, "lon": 44.8858144}, {"type": "node", "id": 26926341, "lat": 65.5162968, "lon": 44.8877912}, {"type": "node", "id": 26926342, "lat": 65.516103, "lon": 44.8910929}, {"type": "node", "id": 533985040, "lat": 65.6304772, "lon": 44.6873122}, {"type": "node", "id": 533985041, "lat": 65.6346799, "lon": 44.7009428}, {"type": "node", "id": 533985042, "lat": 65.6379664, "lon": 44.7116481}, {"type": "node", "id": 533985043, "lat": 65.6408633, "lon": 44.7212599}, {"type": "node", "id": 533985044, "lat": 65.6429421, "lon": 44.7279384}, {"type": "node", "id": 533985045, "lat": 65.6462667, "lon": 44.738814}, {"type": "node", "id": 533985046, "lat": 65.6501649, "lon": 44.7519444}, {"type": "node", "id": 533985078, "lat": 65.6557614, "lon": 44.7707188}, {"type": "node", "id": 533985079, "lat": 65.6574017, "lon": 44.7755917}, {"type": "node", "id": 533985080, "lat": 65.6591486, "lon": 44.7764525}, {"type": "node", "id": 533985089, "lat": 65.6603723, "lon": 44.7753912}, {"type": "node", "id": 533985090, "lat": 65.6618661, "lon": 44.7732699}, {"type": "node", "id": 533985091, "lat": 65.6634053, "lon": 44.7726945}, {"type": "node", "id": 533985098, "lat": 65.6653532, "lon": 44.774942}, {"type": "node", "id": 533985099, "lat": 65.6676957, "lon": 44.7786423}, {"type": "node", "id": 533985121, "lat": 65.6709558, "lon": 44.7837861}, {"type": "node", "id": 533985122, "lat": 65.6721983, "lon": 44.7877117}, {"type": "node", "id": 533985123, "lat": 65.6733391, "lon": 44.7929647}, {"type": "node", "id": 533985221, "lat": 65.6801328, "lon": 44.8250934}, {"type": "node", "id": 533985222, "lat": 65.6817094, "lon": 44.8278645}, {"type": "node", "id": 533985223, "lat": 65.6837061, "lon": 44.8278531}, {"type": "node", "id": 533985224, "lat": 65.6867496, "lon": 44.8266475}, {"type": "node", "id": 533985225, "lat": 65.6889816, "lon": 44.8257277}, {"type": "node", "id": 533985226, "lat": 65.6913384, "lon": 44.8248547}, {"type": "node", "id": 533985227, "lat": 65.6932427, "lon": 44.8256017}, {"type": "node", "id": 533985228, "lat": 65.6958801, "lon": 44.8286663}, {"type": "node", "id": 533985229, "lat": 65.7087773, "lon": 44.843045}, {"type": "node", "id": 533985230, "lat": 65.709691, "lon": 44.8444259}, {"type": "node", "id": 533985231, "lat": 65.7118941, "lon": 44.8505491}, {"type": "node", "id": 533985232, "lat": 65.7164078, "lon": 44.865615}, {"type": "node", "id": 533985233, "lat": 65.718478, "lon": 44.8723211}, {"type": "node", "id": 533985234, "lat": 65.7206822, "lon": 44.8776781}, {"type": "node", "id": 533985235, "lat": 65.7230624, "lon": 44.8795881}, {"type": "node", "id": 533985236, "lat": 65.7320401, "lon": 44.8853615}, {"type": "node", "id": 533985237, "lat": 65.7401065, "lon": 44.8892576}, {"type": "node", "id": 533985238, "lat": 65.7460543, "lon": 44.892034}, {"type": "node", "id": 533985239, "lat": 65.7477719, "lon": 44.8942988}, {"type": "node", "id": 533985240, "lat": 65.7505886, "lon": 44.8995016}, {"type": "node", "id": 533985241, "lat": 65.7520406, "lon": 44.9025172}, {"type": "node", "id": 533985242, "lat": 65.7532746, "lon": 44.9073044}, {"type": "node", "id": 533985243, "lat": 65.753423, "lon": 44.9151114}, {"type": "node", "id": 533985244, "lat": 65.7532217, "lon": 44.9221265}, {"type": "node", "id": 533985245, "lat": 65.752997, "lon": 44.9299682}, {"type": "node", "id": 533986226, "lat": 65.7523655, "lon": 44.9527249}, {"type": "node", "id": 533986239, "lat": 65.7523074, "lon": 44.9608392}, {"type": "node", "id": 533986240, "lat": 65.7535618, "lon": 44.9657587}, {"type": "node", "id": 533986276, "lat": 65.7654203, "lon": 44.9999888}, {"type": "node", "id": 866258627, "lat": 65.5554879, "lon": 44.6107155}, {"type": "node", "id": 1544309434, "lat": 65.7801624, "lon": 45.0317926}, {"type": "node", "id": 1544309439, "lat": 65.7764601, "lon": 45.0269249}, {"type": "node", "id": 1544309443, "lat": 65.7727826, "lon": 45.0221374}, {"type": "node", "id": 1544309445, "lat": 65.7666533, "lon": 45.0108078}, {"type": "node", "id": 1544309460, "lat": 65.7682739, "lon": 45.0161293}, {"type": "node", "id": 1544309464, "lat": 65.7670761, "lon": 45.013726}, {"type": "node", "id": 2353120930, "lat": 65.5401576, "lon": 44.7328706}, {"type": "node", "id": 2353121392, "lat": 65.5608749, "lon": 44.7341971}, {"type": "node", "id": 2355915717, "lat": 65.5162235, "lon": 44.879853}, {"type": "node", "id": 2355915720, "lat": 65.516253, "lon": 44.8778837}, {"type": "node", "id": 2355915723, "lat": 65.516361, "lon": 44.8840505}, {"type": "node", "id": 2360198062, "lat": 65.533929, "lon": 44.740131}, {"type": "node", "id": 2360256856, "lat": 65.5848266, "lon": 44.6998917}, {"type": "node", "id": 2360256859, "lat": 65.5850485, "lon": 44.6994814}, {"type": "node", "id": 2360256991, "lat": 65.6036756, "lon": 44.6768824}, {"type": "node", "id": 2657935767, "lat": 65.6428455, "lon": 44.7276423}, {"type": "node", "id": 3714064314, "lat": 65.7313703, "lon": 44.8849818}, {"type": "node", "id": 3910429790, "lat": 65.7746666, "lon": 45.0244038}, {"type": "node", "id": 4045598144, "lat": 65.500662, "lon": 44.8148458}, {"type": "node", "id": 4045598182, "lat": 65.5016239, "lon": 44.8211825}, {"type": "node", "id": 4045598503, "lat": 65.5018824, "lon": 44.8219168}, {"type": "node", "id": 4045598509, "lat": 65.5018746, "lon": 44.8139538}, {"type": "node", "id": 4045598513, "lat": 65.5018639, "lon": 44.8141237}, {"type": "node", "id": 4045598521, "lat": 65.5019401, "lon": 44.8144142}, {"type": "node", "id": 4045598533, "lat": 65.5020318, "lon": 44.813552}, {"type": "node", "id": 4045598538, "lat": 65.5020607, "lon": 44.8156215}, {"type": "node", "id": 4045598540, "lat": 65.5020443, "lon": 44.814525}, {"type": "node", "id": 4045598542, "lat": 65.5020465, "lon": 44.8178907}, {"type": "node", "id": 4045598545, "lat": 65.5020657, "lon": 44.8152269}, {"type": "node", "id": 4045598547, "lat": 65.5020963, "lon": 44.8147023}, {"type": "node", "id": 4045598558, "lat": 65.5021638, "lon": 44.8131889}, {"type": "node", "id": 4045598565, "lat": 65.5021844, "lon": 44.8166789}, {"type": "node", "id": 4045598571, "lat": 65.5022367, "lon": 44.8195827}, {"type": "node", "id": 4045598577, "lat": 65.5022464, "lon": 44.8169925}, {"type": "node", "id": 4045598578, "lat": 65.5022601, "lon": 44.8162099}, {"type": "node", "id": 4045598695, "lat": 65.5023498, "lon": 44.8128028}, {"type": "node", "id": 4045598710, "lat": 65.5024302, "lon": 44.8171993}, {"type": "node", "id": 4045598713, "lat": 65.5024714, "lon": 44.8144035}, {"type": "node", "id": 4045598716, "lat": 65.5025225, "lon": 44.8138091}, {"type": "node", "id": 4045598717, "lat": 65.5024884, "lon": 44.8173397}, {"type": "node", "id": 4045598733, "lat": 65.5025528, "lon": 44.8123862}, {"type": "node", "id": 4045598741, "lat": 65.5026185, "lon": 44.8068192}, {"type": "node", "id": 4045598743, "lat": 65.5025881, "lon": 44.8057403}, {"type": "node", "id": 4045598744, "lat": 65.5026089, "lon": 44.810206}, {"type": "node", "id": 4045598753, "lat": 65.5026976, "lon": 44.80514}, {"type": "node", "id": 4045598772, "lat": 65.5027458, "lon": 44.815382}, {"type": "node", "id": 4045598799, "lat": 65.5028967, "lon": 44.8046585}, {"type": "node", "id": 4045598814, "lat": 65.5030918, "lon": 44.8044456}, {"type": "node", "id": 4045598830, "lat": 65.5033139, "lon": 44.8044342}, {"type": "node", "id": 4045598831, "lat": 65.5036435, "lon": 44.8136252}, {"type": "node", "id": 4045598834, "lat": 65.5034066, "lon": 44.8047653}, {"type": "node", "id": 4045598835, "lat": 65.5034579, "lon": 44.8054495}, {"type": "node", "id": 4045598836, "lat": 65.5045254, "lon": 44.8080995}, {"type": "node", "id": 4045598837, "lat": 65.5058037, "lon": 44.8076446}, {"type": "node", "id": 4045598838, "lat": 65.5060739, "lon": 44.8073653}, {"type": "node", "id": 4045598839, "lat": 65.5068202, "lon": 44.8064132}, {"type": "node", "id": 4045598840, "lat": 65.5077211, "lon": 44.8061625}, {"type": "node", "id": 4045598841, "lat": 65.5081802, "lon": 44.8062252}, {"type": "node", "id": 4045598842, "lat": 65.5084141, "lon": 44.8057864}, {"type": "node", "id": 4045598843, "lat": 65.5095921, "lon": 44.8007298}, {"type": "node", "id": 4045617061, "lat": 65.4938879, "lon": 44.8558923}, {"type": "node", "id": 4045617063, "lat": 65.4938987, "lon": 44.8546856}, {"type": "node", "id": 4045617064, "lat": 65.4939442, "lon": 44.8543626}, {"type": "node", "id": 4045617073, "lat": 65.4941483, "lon": 44.8535076}, {"type": "node", "id": 4045617085, "lat": 65.4944118, "lon": 44.8513209}, {"type": "node", "id": 4045617103, "lat": 65.494853, "lon": 44.8473464}, {"type": "node", "id": 4045617117, "lat": 65.4952452, "lon": 44.8456916}, {"type": "node", "id": 4045617121, "lat": 65.495521, "lon": 44.8448642}, {"type": "node", "id": 4045617122, "lat": 65.4956803, "lon": 44.8438152}, {"type": "node", "id": 4045617123, "lat": 65.4958152, "lon": 44.843106}, {"type": "node", "id": 4045617130, "lat": 65.4969366, "lon": 44.838969}, {"type": "node", "id": 4045617131, "lat": 65.4970469, "lon": 44.838378}, {"type": "node", "id": 4045617134, "lat": 65.4971265, "lon": 44.8376835}, {"type": "node", "id": 4045617136, "lat": 65.4974207, "lon": 44.8371221}, {"type": "node", "id": 4045617137, "lat": 65.4975984, "lon": 44.8370334}, {"type": "node", "id": 4045617142, "lat": 65.4984072, "lon": 44.8347433}, {"type": "node", "id": 4045617144, "lat": 65.4985481, "lon": 44.8209878}, {"type": "node", "id": 4045617146, "lat": 65.4987687, "lon": 44.8229824}, {"type": "node", "id": 4045617147, "lat": 65.4987932, "lon": 44.819924}, {"type": "node", "id": 4045617148, "lat": 65.4988239, "lon": 44.8339011}, {"type": "node", "id": 4045617149, "lat": 65.4991364, "lon": 44.8191557}, {"type": "node", "id": 4045617150, "lat": 65.4991609, "lon": 44.8325418}, {"type": "node", "id": 4045617152, "lat": 65.4991854, "lon": 44.8293061}, {"type": "node", "id": 4045617156, "lat": 65.4992589, "lon": 44.8314189}, {"type": "node", "id": 4045617163, "lat": 65.4999513, "lon": 44.8165848}, {"type": "node", "id": 4045617175, "lat": 65.5008291, "lon": 44.8143528}, {"type": "node", "id": 4045638925, "lat": 65.5108656, "lon": 44.7959782}, {"type": "node", "id": 4045638926, "lat": 65.5111488, "lon": 44.7940834}, {"type": "node", "id": 4045638927, "lat": 65.5116297, "lon": 44.7899846}, {"type": "node", "id": 4045638928, "lat": 65.5120678, "lon": 44.7866204}, {"type": "node", "id": 4045638929, "lat": 65.5121266, "lon": 44.7853315}, {"type": "node", "id": 4045638930, "lat": 65.5124151, "lon": 44.7843261}, {"type": "node", "id": 4045638931, "lat": 65.5126394, "lon": 44.783759}, {"type": "node", "id": 4045638932, "lat": 65.5127783, "lon": 44.7827536}, {"type": "node", "id": 4045638933, "lat": 65.5129921, "lon": 44.7782681}, {"type": "node", "id": 4045638934, "lat": 65.5130562, "lon": 44.7820189}, {"type": "node", "id": 4045638935, "lat": 65.5130829, "lon": 44.7799953}, {"type": "node", "id": 4045638936, "lat": 65.5131203, "lon": 44.7814002}, {"type": "node", "id": 4045638937, "lat": 65.5131951, "lon": 44.7765409}, {"type": "node", "id": 4045638938, "lat": 65.5132111, "lon": 44.7753551}, {"type": "node", "id": 4045638939, "lat": 65.5132699, "lon": 44.7718749}, {"type": "node", "id": 4045638940, "lat": 65.5133607, "lon": 44.7683174}, {"type": "node", "id": 4045638941, "lat": 65.5133995, "lon": 44.766836}, {"type": "node", "id": 4045638942, "lat": 65.5134335, "lon": 44.7675014}, {"type": "node", "id": 4045638943, "lat": 65.5134826, "lon": 44.7657423}, {"type": "node", "id": 4045638944, "lat": 65.513917, "lon": 44.7619326}, {"type": "node", "id": 4045638945, "lat": 65.5144345, "lon": 44.7577492}, {"type": "node", "id": 4045638946, "lat": 65.5146725, "lon": 44.7564094}, {"type": "node", "id": 4045638947, "lat": 65.5148161, "lon": 44.7552154}, {"type": "node", "id": 4045638948, "lat": 65.5152694, "lon": 44.7542311}, {"type": "node", "id": 4045638949, "lat": 65.5155715, "lon": 44.7529915}, {"type": "node", "id": 4045638950, "lat": 65.5164403, "lon": 44.7495281}, {"type": "node", "id": 4045638951, "lat": 65.5170824, "lon": 44.7477235}, {"type": "node", "id": 4045638952, "lat": 65.5174148, "lon": 44.746566}, {"type": "node", "id": 4045638953, "lat": 65.5180078, "lon": 44.7439502}, {"type": "node", "id": 4045638954, "lat": 65.518563, "lon": 44.7413253}, {"type": "node", "id": 4045638955, "lat": 65.5191107, "lon": 44.7378437}, {"type": "node", "id": 4045638956, "lat": 65.5193939, "lon": 44.734918}, {"type": "node", "id": 4045638957, "lat": 65.5198245, "lon": 44.7308075}, {"type": "node", "id": 4045638958, "lat": 65.5200662, "lon": 44.7283649}, {"type": "node", "id": 4045638959, "lat": 65.5200889, "lon": 44.72749}, {"type": "node", "id": 4045638960, "lat": 65.5202966, "lon": 44.7253117}, {"type": "node", "id": 4045638961, "lat": 65.5204099, "lon": 44.7229237}, {"type": "node", "id": 4045638962, "lat": 65.5205798, "lon": 44.7212011}, {"type": "node", "id": 4045638963, "lat": 65.5210557, "lon": 44.7179656}, {"type": "node", "id": 4045638964, "lat": 65.5212181, "lon": 44.7169813}, {"type": "node", "id": 4045638966, "lat": 65.5215315, "lon": 44.7160334}, {"type": "node", "id": 4045638967, "lat": 65.5227173, "lon": 44.7137731}, {"type": "node", "id": 4045638968, "lat": 65.5236991, "lon": 44.7112666}, {"type": "node", "id": 4045638969, "lat": 65.5244468, "lon": 44.7098995}, {"type": "node", "id": 4045638970, "lat": 65.525606, "lon": 44.7070194}, {"type": "node", "id": 4045638971, "lat": 65.526331, "lon": 44.7046133}, {"type": "node", "id": 4045638972, "lat": 65.5268256, "lon": 44.7025079}, {"type": "node", "id": 4045638973, "lat": 65.527845, "lon": 44.6996916}, {"type": "node", "id": 4045638974, "lat": 65.5280225, "lon": 44.6991265}, {"type": "node", "id": 4045638975, "lat": 65.5289815, "lon": 44.6969573}, {"type": "node", "id": 4045638976, "lat": 65.5302953, "lon": 44.6934483}, {"type": "node", "id": 4045638977, "lat": 65.5310201, "lon": 44.6916893}, {"type": "node", "id": 4045638978, "lat": 65.5312101, "lon": 44.6860396}, {"type": "node", "id": 4045638979, "lat": 65.5312208, "lon": 44.6872608}, {"type": "node", "id": 4045638980, "lat": 65.5312875, "lon": 44.6876314}, {"type": "node", "id": 4045638981, "lat": 65.531413, "lon": 44.6846475}, {"type": "node", "id": 4045638982, "lat": 65.5315064, "lon": 44.6880503}, {"type": "node", "id": 4045638983, "lat": 65.5315298, "lon": 44.6896933}, {"type": "node", "id": 4045638984, "lat": 65.5315398, "lon": 44.6835003}, {"type": "node", "id": 4045638985, "lat": 65.5315664, "lon": 44.6890815}, {"type": "node", "id": 4045638986, "lat": 65.5317853, "lon": 44.6827173}, {"type": "node", "id": 4045638987, "lat": 65.5323512, "lon": 44.681612}, {"type": "node", "id": 4045638988, "lat": 65.5326969, "lon": 44.6810159}, {"type": "node", "id": 4045638989, "lat": 65.5330159, "lon": 44.6803618}, {"type": "node", "id": 4045638990, "lat": 65.5332561, "lon": 44.67993}, {"type": "node", "id": 4045638991, "lat": 65.5339287, "lon": 44.6791405}, {"type": "node", "id": 4045638992, "lat": 65.5343798, "lon": 44.6782543}, {"type": "node", "id": 4045638993, "lat": 65.5348682, "lon": 44.6768558}, {"type": "node", "id": 4045638994, "lat": 65.5352552, "lon": 44.67596}, {"type": "node", "id": 4045638995, "lat": 65.5357656, "lon": 44.6745763}, {"type": "node", "id": 4045638996, "lat": 65.536026, "lon": 44.6733003}, {"type": "node", "id": 4045638997, "lat": 65.5364072, "lon": 44.6709307}, {"type": "node", "id": 4047501745, "lat": 65.5315361, "lon": 44.6885614, "tags": {"ford": "yes"}}, {"type": "node", "id": 4047508910, "lat": 65.5368744, "lon": 44.669441}, {"type": "node", "id": 4047508914, "lat": 65.5376579, "lon": 44.6675491}, {"type": "node", "id": 4047508915, "lat": 65.5381051, "lon": 44.666524}, {"type": "node", "id": 4047508916, "lat": 65.538504, "lon": 44.6653958}, {"type": "node", "id": 4047508917, "lat": 65.5385097, "lon": 44.6643088}, {"type": "node", "id": 4047508918, "lat": 65.5385438, "lon": 44.6639373}, {"type": "node", "id": 4047508919, "lat": 65.5385495, "lon": 44.6648867}, {"type": "node", "id": 4047508920, "lat": 65.5393984, "lon": 44.6614744}, {"type": "node", "id": 4047508921, "lat": 65.5396263, "lon": 44.6605525}, {"type": "node", "id": 4047508922, "lat": 65.5400935, "lon": 44.6597132}, {"type": "node", "id": 4047508924, "lat": 65.5403784, "lon": 44.6588739}, {"type": "node", "id": 4047508926, "lat": 65.5409708, "lon": 44.6571127}, {"type": "node", "id": 4047508927, "lat": 65.5414608, "lon": 44.6562321}, {"type": "node", "id": 4047508928, "lat": 65.5417228, "lon": 44.6557643}, {"type": "node", "id": 4047508930, "lat": 65.542264, "lon": 44.6543471}, {"type": "node", "id": 4047508931, "lat": 65.5428622, "lon": 44.6528336}, {"type": "node", "id": 4047508934, "lat": 65.5433464, "lon": 44.6509898}, {"type": "node", "id": 4047508937, "lat": 65.5439616, "lon": 44.6479077}, {"type": "node", "id": 4047508939, "lat": 65.5443489, "lon": 44.6462016}, {"type": "node", "id": 4047508942, "lat": 65.5445938, "lon": 44.6454173}, {"type": "node", "id": 4047508943, "lat": 65.5450153, "lon": 44.6443716}, {"type": "node", "id": 4047508946, "lat": 65.5457216, "lon": 44.6428856}, {"type": "node", "id": 4047508948, "lat": 65.5462457, "lon": 44.6421151}, {"type": "node", "id": 4047508951, "lat": 65.5467981, "lon": 44.6415097}, {"type": "node", "id": 4047508953, "lat": 65.5471285, "lon": 44.6406428}, {"type": "node", "id": 4047508954, "lat": 65.5472481, "lon": 44.6402576}, {"type": "node", "id": 4047508955, "lat": 65.5476012, "lon": 44.6401613}, {"type": "node", "id": 4047508956, "lat": 65.5477607, "lon": 44.639831}, {"type": "node", "id": 4047508958, "lat": 65.5479828, "lon": 44.6391293}, {"type": "node", "id": 4047508960, "lat": 65.5482106, "lon": 44.6384689}, {"type": "node", "id": 4047508961, "lat": 65.5484612, "lon": 44.6382212}, {"type": "node", "id": 4047508963, "lat": 65.5488827, "lon": 44.6381524}, {"type": "node", "id": 4047508966, "lat": 65.5494351, "lon": 44.6384826}, {"type": "node", "id": 4047525264, "lat": 65.5496822, "lon": 44.6390918}, {"type": "node", "id": 4047525265, "lat": 65.5499331, "lon": 44.6389433}, {"type": "node", "id": 4047525266, "lat": 65.5499536, "lon": 44.6368775}, {"type": "node", "id": 4047525267, "lat": 65.5500355, "lon": 44.6374342}, {"type": "node", "id": 4047525268, "lat": 65.5500406, "lon": 44.6361106}, {"type": "node", "id": 4047525269, "lat": 65.5500662, "lon": 44.6387454}, {"type": "node", "id": 4047525270, "lat": 65.5501993, "lon": 44.6380156}, {"type": "node", "id": 4047525271, "lat": 65.5502915, "lon": 44.6348983}, {"type": "node", "id": 4047525272, "lat": 65.5506755, "lon": 44.634255}, {"type": "node", "id": 4047525274, "lat": 65.5516124, "lon": 44.6334757}, {"type": "node", "id": 4047525275, "lat": 65.5518223, "lon": 44.6331046}, {"type": "node", "id": 4047525276, "lat": 65.5523701, "lon": 44.6323995}, {"type": "node", "id": 4047525277, "lat": 65.553097, "lon": 44.6169988}, {"type": "node", "id": 4047525278, "lat": 65.5531431, "lon": 44.616071}, {"type": "node", "id": 4047525279, "lat": 65.5533069, "lon": 44.6193491}, {"type": "node", "id": 4047525280, "lat": 65.5535731, "lon": 44.6221942}, {"type": "node", "id": 4047525281, "lat": 65.5536243, "lon": 44.6246187}, {"type": "node", "id": 4047525283, "lat": 65.5539929, "lon": 44.6265237}, {"type": "node", "id": 4047525284, "lat": 65.5540288, "lon": 44.6301729}, {"type": "node", "id": 4047525286, "lat": 65.5543308, "lon": 44.6127558}, {"type": "node", "id": 4047525287, "lat": 65.5543513, "lon": 44.6277731}, {"type": "node", "id": 4047525288, "lat": 65.5543513, "lon": 44.6294802}, {"type": "node", "id": 4047527589, "lat": 65.5544536, "lon": 44.6287132}, {"type": "node", "id": 4320937657, "lat": 65.5167539, "lon": 44.8659626}, {"type": "node", "id": 4320937658, "lat": 65.5202839, "lon": 44.8434662}, {"type": "node", "id": 4320937659, "lat": 65.5263549, "lon": 44.7832214}, {"type": "node", "id": 4320937660, "lat": 65.5407193, "lon": 44.7327849}, {"type": "node", "id": 4320937661, "lat": 65.5763915, "lon": 44.7189673}, {"type": "node", "id": 4704785335, "lat": 65.6551029, "lon": 44.7685095}, {"type": "node", "id": 4704785336, "lat": 65.6418955, "lon": 44.7246244}, {"type": "node", "id": 4704805764, "lat": 65.7675896, "lon": 45.0150554}, {"type": "node", "id": 4704805765, "lat": 65.7657698, "lon": 45.0020336}, {"type": "node", "id": 4704805766, "lat": 65.752247, "lon": 44.9569431}, {"type": "node", "id": 4704805767, "lat": 65.7527818, "lon": 44.9633161}, {"type": "node", "id": 4704805768, "lat": 65.7535115, "lon": 44.9108937}, {"type": "node", "id": 4704805769, "lat": 65.7526745, "lon": 44.90438}, {"type": "node", "id": 4704805770, "lat": 65.7471126, "lon": 44.8931701}, {"type": "node", "id": 4704806346, "lat": 65.716025, "lon": 44.8643371}, {"type": "node", "id": 4704806372, "lat": 65.7251697, "lon": 44.881228}, {"type": "node", "id": 4704806442, "lat": 65.7365798, "lon": 44.887554}, {"type": "node", "id": 4704806443, "lat": 65.7269536, "lon": 44.8826163}, {"type": "node", "id": 4704806444, "lat": 65.7198362, "lon": 44.8763955}, {"type": "node", "id": 4704806445, "lat": 65.7191167, "lon": 44.8743573}, {"type": "node", "id": 4704806446, "lat": 65.7110363, "lon": 44.8476841}, {"type": "node", "id": 4704806447, "lat": 65.7104489, "lon": 44.8458712}, {"type": "node", "id": 4704806448, "lat": 65.6924767, "lon": 44.8248474}, {"type": "node", "id": 4704806449, "lat": 65.691865, "lon": 44.8246725}, {"type": "node", "id": 4704806450, "lat": 65.681076, "lon": 44.827316}, {"type": "node", "id": 4704806451, "lat": 65.6804539, "lon": 44.8261774}, {"type": "node", "id": 4704806452, "lat": 65.6717883, "lon": 44.785845}, {"type": "node", "id": 4704806453, "lat": 65.6714192, "lon": 44.7847243}, {"type": "node", "id": 4704806454, "lat": 65.6640609, "lon": 44.7731771}, {"type": "node", "id": 4704806455, "lat": 65.6626749, "lon": 44.7727831}, {"type": "node", "id": 4704806456, "lat": 65.6596315, "lon": 44.7762446}, {"type": "node", "id": 4704806457, "lat": 65.6583116, "lon": 44.7763584}, {"type": "node", "id": 4704806458, "lat": 65.6577614, "lon": 44.7759738}, {"type": "node", "id": 4704806459, "lat": 65.6569275, "lon": 44.7746003}, {"type": "node", "id": 4704876914, "lat": 65.7810477, "lon": 45.032996}, {"type": "node", "id": 5709123053, "lat": 65.5035933, "lon": 44.8066825}, {"type": "node", "id": 5709123054, "lat": 65.5034554, "lon": 44.8059475}, {"type": "node", "id": 5709123055, "lat": 65.5035066, "lon": 44.8062748}, {"type": "node", "id": 5709123056, "lat": 65.5038491, "lon": 44.8072135}, {"type": "node", "id": 5709123057, "lat": 65.5037335, "lon": 44.8069346}, {"type": "node", "id": 5709123058, "lat": 65.504116, "lon": 44.8079216}, {"type": "node", "id": 5709123059, "lat": 65.5044586, "lon": 44.8079914}, {"type": "node", "id": 5709123060, "lat": 65.5043518, "lon": 44.8079807}, {"type": "node", "id": 5709123061, "lat": 65.5039314, "lon": 44.807632}, {"type": "node", "id": 5709123062, "lat": 65.5046699, "lon": 44.8083454}, {"type": "node", "id": 5709123063, "lat": 65.5048122, "lon": 44.8084044}, {"type": "node", "id": 5709123064, "lat": 65.505048, "lon": 44.8083883}, {"type": "node", "id": 5709123065, "lat": 65.5051614, "lon": 44.8083293}, {"type": "node", "id": 5709123066, "lat": 65.5054528, "lon": 44.8079807}, {"type": "node", "id": 5709123067, "lat": 65.5062312, "lon": 44.8070204}, {"type": "node", "id": 5709123068, "lat": 65.5063068, "lon": 44.8065215}, {"type": "node", "id": 7889812829, "lat": 65.7813113, "lon": 45.0333813}, {"type": "node", "id": 7916117412, "lat": 65.6608039, "lon": 44.7746891}, {"type": "node", "id": 7916117413, "lat": 65.6612593, "lon": 44.7739917}, {"type": "node", "id": 7919509630, "lat": 65.5066871, "lon": 44.8064733}, {"type": "node", "id": 7919509631, "lat": 65.5065337, "lon": 44.8064684}, {"type": "node", "id": 9788265202, "lat": 65.5019751, "lon": 44.8233014}, {"type": "node", "id": 9788265203, "lat": 65.5021064, "lon": 44.8226094}, {"type": "node", "id": 9788265204, "lat": 65.5021108, "lon": 44.8224646}, {"type": "node", "id": 9788265205, "lat": 65.5021008, "lon": 44.8223358}, {"type": "node", "id": 9788265206, "lat": 65.5020763, "lon": 44.8222607}, {"type": "node", "id": 9788265207, "lat": 65.5019862, "lon": 44.8221776}, {"type": "node", "id": 9788265208, "lat": 65.5019251, "lon": 44.8220891}, {"type": "node", "id": 9788265209, "lat": 65.5019006, "lon": 44.8220327}, {"type": "node", "id": 9788265210, "lat": 65.5018828, "lon": 44.8142946}, {"type": "node", "id": 9788277808, "lat": 65.5029538, "lon": 44.8136884}, {"type": "node", "id": 9788277809, "lat": 65.5025301, "lon": 44.8130822}, {"type": "node", "id": 9788277810, "lat": 65.5020886, "lon": 44.8149222}, {"type": "node", "id": 9788277811, "lat": 65.5020774, "lon": 44.8146003}, {"type": "node", "id": 9788277812, "lat": 65.5026269, "lon": 44.8054218}, {"type": "node", "id": 9788277813, "lat": 65.5027792, "lon": 44.8048505}, {"type": "node", "id": 9788277814, "lat": 65.5032007, "lon": 44.8043865}, {"type": "node", "id": 9788354716, "lat": 65.5009997, "lon": 44.8146325}, {"type": "node", "id": 9788365817, "lat": 65.5016693, "lon": 44.8151046}, {"type": "node", "id": 9788365818, "lat": 65.5013445, "lon": 44.8148417}, {"type": "node", "id": 9788365819, "lat": 65.501191, "lon": 44.8147881}, {"type": "node", "id": 9788365820, "lat": 65.5019206, "lon": 44.8155338}, {"type": "node", "id": 9788365821, "lat": 65.5017938, "lon": 44.8153567}, {"type": "node", "id": 9788365822, "lat": 65.5015247, "lon": 44.8149061}, {"type": "node", "id": 11697333894, "lat": 65.7731503, "lon": 45.0225797}, {"type": "node", "id": 12117354975, "lat": 65.5187612, "lon": 44.8536613, "tags": {"distance:backward": "15", "highway": "milestone", "ref": "15"}}, {"type": "node", "id": 12117372522, "lat": 65.5164032, "lon": 44.8734454, "tags": {"distance:backward": "16", "highway": "milestone", "ref": "16"}}, {"type": "node", "id": 12117374413, "lat": 65.5302914, "lon": 44.7521196, "tags": {"distance:backward": "10", "highway": "milestone", "ref": "10"}}, {"type": "node", "id": 12117374414, "lat": 65.553866, "lon": 44.7337767, "tags": {"distance:backward": "7", "highway": "milestone", "ref": "7"}}, {"type": "node", "id": 12117381960, "lat": 65.5210897, "lon": 44.8349582, "tags": {"distance:backward": "14", "highway": "milestone", "ref": "14"}}, {"type": "node", "id": 12117387245, "lat": 65.5231575, "lon": 44.8140129, "tags": {"distance:backward": "13", "highway": "milestone", "ref": "13"}}, {"type": "way", "id": 42702154, "nodes": [7916117413, 533985090, 4704806455, 533985091, 4704806454, 533985098, 533985099, 533985121, 4704806453, 4704806452, 533985122, 533985123, 533985221, 4704806451, 4704806450, 533985222, 533985223, 533985224, 533985225, 533985226, 4704806449, 4704806448, 533985227, 533985228, 533985229, 533985230, 4704806447, 4704806446, 533985231, 4704806346, 533985232, 533985233, 4704806445, 4704806444, 533985234, 533985235, 4704806372, 4704806443, 3714064314, 533985236, 4704806442, 533985237, 533985238, 4704805770, 533985239, 533985240, 533985241, 4704805769, 533985242, 4704805768, 533985243, 533985244, 533985245, 533986226, 4704805766, 533986239, 4704805767, 533986240, 533986276, 4704805765, 1544309445, 1544309464, 4704805764, 1544309460, 1544309443, 11697333894, 3910429790, 1544309439, 1544309434, 4704876914, 7889812829], "tags": {"highway": "tertiary", "ref": "11\u041a-502", "tracktype": "unknown"}}, {"type": "way", "id": 90478296, "nodes": [26925952, 26925953, 26925954, 26925955, 2360256991, 26925956, 26926251, 26926252, 26926253, 26926254, 26926255, 26926256, 26926257, 26926258, 26926259, 26926260, 2360256859, 2360256856, 26926261, 26926262, 26926263, 26926264, 26926265, 26926266, 26926267, 4320937661, 26926268, 26926269, 26926270, 26926271, 26926272, 26926273, 26926274, 26926275, 26926276, 26926277, 26926278, 26926279, 26926280, 26926281, 2353121392, 26926282, 26926283, 26926284, 26926285, 12117374414, 26926286, 26926287, 26926288, 26926289, 26926290, 26926291, 26926292, 26926293, 4320937660, 2353120930, 26926294, 26926295, 26926296, 26926297, 26926298, 26926299, 2360198062, 26926300, 26926301, 26926302, 26926303, 26926304, 26926305, 12117374413, 26926306, 26926307, 26926308, 26926309, 26926310, 26926311, 26926312, 26926313, 26926314, 4320937659, 26926315, 26926316, 26926317, 26926318, 26926319, 26926320, 26926321, 26926322, 12117387245, 26926323, 26926324, 26926325, 26926326, 12117381960, 26926327, 26926328, 4320937658, 26926329, 26926330, 26926331, 12117354975, 26926332, 26926333, 26926334, 26926335, 4320937657, 26926336, 26926337, 12117372522, 26926338, 2355915720, 2355915717, 26926339, 2355915723, 26926340, 26926341, 26926342], "tags": {"highway": "secondary", "maxspeed": "RU:rural", "ref": "11\u041a-462"}}, {"type": "way", "id": 402135678, "nodes": [866258627, 4047525286, 4047525278, 4047525277, 4047525279, 4047525280, 4047525281, 4047525283, 4047525287, 4047527589, 4047525288, 4047525284, 4047525276, 4047525275, 4047525274, 4047525272, 4047525271, 4047525268, 4047525266, 4047525267, 4047525270, 4047525269, 4047525265, 4047525264, 4047508966, 4047508963, 4047508961, 4047508960, 4047508958, 4047508956, 4047508955, 4047508954, 4047508953, 4047508951, 4047508948, 4047508946, 4047508943, 4047508942, 4047508939, 4047508937, 4047508934, 4047508931, 4047508930, 4047508928, 4047508927, 4047508926, 4047508924, 4047508922, 4047508921, 4047508920, 4047508918, 4047508917, 4047508919, 4047508916, 4047508915, 4047508914, 4047508910, 4045638997, 4045638996, 4045638995, 4045638994, 4045638993, 4045638992, 4045638991, 4045638990, 4045638989, 4045638988, 4045638987, 4045638986, 4045638984, 4045638981, 4045638978, 4045638979, 4045638980, 4045638982, 4047501745, 4045638985, 4045638983, 4045638977, 4045638976, 4045638975, 4045638974, 4045638973, 4045638972, 4045638971, 4045638970, 4045638969, 4045638968, 4045638967, 4045638966, 4045638964, 4045638963, 4045638962, 4045638961, 4045638960, 4045638959, 4045638958, 4045638957, 4045638956, 4045638955, 4045638954, 4045638953, 4045638952, 4045638951, 4045638950, 4045638949, 4045638948, 4045638947, 4045638946, 4045638945, 4045638944, 4045638943, 4045638941, 4045638942, 4045638940, 4045638939, 4045638938, 4045638937, 4045638933, 4045638935, 4045638936, 4045638934, 4045638932, 4045638931, 4045638930, 4045638929, 4045638928, 4045638927, 4045638926, 4045638925, 4045598843, 4045598842, 4045598841, 4045598840, 4045598839, 7919509630], "tags": {"highway": "unclassified"}}, {"type": "way", "id": 402135680, "nodes": [4045598733, 4045598695, 4045598558, 4045598533, 4045598509, 4045598513, 9788265210, 4045598521, 4045598540, 9788277811, 4045598547, 9788277810, 4045598545, 4045598538, 4045598578], "tags": {"highway": "residential"}}, {"type": "way", "id": 402135681, "nodes": [4045598182, 4045598542, 4045598565, 4045598578, 4045598713, 4045598716, 9788277809, 4045598733, 4045598744, 4045598741, 4045598743, 9788277812, 4045598753, 9788277813, 4045598799, 4045598814, 9788277814, 4045598830], "tags": {"highway": "residential", "name": "\u0426\u0435\u043d\u0442\u0440\u0430\u043b\u044c\u043d\u0430\u044f \u0443\u043b\u0438\u0446\u0430"}}, {"type": "way", "id": 402135682, "nodes": [4045598716, 9788277808, 4045598831], "tags": {"highway": "residential"}}, {"type": "way", "id": 402135684, "nodes": [4045598717, 4045598710, 4045598577, 4045598565], "tags": {"highway": "residential"}}, {"type": "way", "id": 402135685, "nodes": [9788265202, 9788265203, 9788265204, 9788265205, 9788265206, 9788265207, 9788265208, 9788265209, 4045598503, 4045598571, 4045598717, 4045598772], "tags": {"highway": "residential", "name": "\u0421\u0435\u0432\u0435\u0440\u043d\u0430\u044f \u0443\u043b\u0438\u0446\u0430"}}, {"type": "way", "id": 402137479, "nodes": [4045617061, 4045617063, 4045617064, 4045617073, 4045617085, 4045617103, 4045617117, 4045617121, 4045617122, 4045617123, 4045617130, 4045617131, 4045617134, 4045617136, 4045617137, 4045617142, 4045617148, 4045617150, 4045617156, 4045617152, 4045617146, 4045617144, 4045617147, 4045617149, 4045617163, 4045598144, 4045617175, 9788354716, 9788365819, 9788365818, 9788365822, 9788365817, 9788365821, 9788365820, 4045598538], "tags": {"highway": "unclassified"}}, {"type": "way", "id": 848327513, "nodes": [26925945, 533985040, 533985041, 533985042, 533985043, 4704785336, 2657935767, 533985044, 533985045, 533985046, 4704785335, 533985078, 4704806459, 533985079, 4704806458, 4704806457, 533985080, 4704806456, 533985089, 7916117412], "tags": {"highway": "tertiary", "ref": "11\u041a-502", "tracktype": "unknown"}}, {"type": "way", "id": 848772204, "nodes": [7919509630, 7919509631], "tags": {"bridge": "yes", "highway": "unclassified", "layer": "1"}}, {"type": "way", "id": 848772205, "nodes": [7919509631, 5709123068, 5709123067, 4045598838, 4045598837, 5709123066, 5709123065, 5709123064, 5709123063, 5709123062, 4045598836, 5709123059, 5709123060, 5709123058, 5709123061, 5709123056, 5709123057, 5709123053, 5709123055, 5709123054, 4045598835, 4045598834, 4045598830], "tags": {"highway": "unclassified"}}]}